LICENSE
README.md
setup.py
zkw_db/__init__.py
zkw_db/create_table.py
zkw_db/my_class.py
zkw_db/my_db.py
zkw_db.egg-info/PKG-INFO
zkw_db.egg-info/SOURCES.txt
zkw_db.egg-info/dependency_links.txt
zkw_db.egg-info/top_level.txt