Metadata-Version: 2.1
Name: zkw-db
Version: 0.1
Summary: string to date
Author-email: zkw8119@163.com
License: MIT
Platform: any
License-File: LICENSE
